datalad_deprecated/__init__.py
datalad_deprecated/_version.py
datalad_deprecated/annotate_paths.py
datalad_deprecated/auto.py
datalad_deprecated/conftest.py
datalad_deprecated/diff.py
datalad_deprecated/gitrepo.py
datalad_deprecated/ls.py
datalad_deprecated/ls_webui.py
datalad_deprecated/publish.py
datalad_deprecated/sibling_webui.py
datalad_deprecated/utils.py
datalad_deprecated/metadata/__init__.py
datalad_deprecated/metadata/aggregate.py
datalad_deprecated/metadata/annotate_paths.py
datalad_deprecated/metadata/common_opts.py
datalad_deprecated/metadata/consts.py
datalad_deprecated/metadata/definitions.py
datalad_deprecated/metadata/extract_metadata.py
datalad_deprecated/metadata/metadata.py
datalad_deprecated/metadata/search.py
datalad_deprecated/metadata/utils.py
datalad_deprecated/metadata/extractors/__init__.py
datalad_deprecated/metadata/extractors/annex.py
datalad_deprecated/metadata/extractors/audio.py
datalad_deprecated/metadata/extractors/base.py
datalad_deprecated/metadata/extractors/datacite.py
datalad_deprecated/metadata/extractors/datalad_core.py
datalad_deprecated/metadata/extractors/datalad_rfc822.py
datalad_deprecated/metadata/extractors/exif.py
datalad_deprecated/metadata/extractors/frictionless_datapackage.py
datalad_deprecated/metadata/extractors/image.py
datalad_deprecated/metadata/extractors/xmp.py
datalad_deprecated/metadata/extractors/tests/__init__.py
datalad_deprecated/metadata/extractors/tests/test_audio.py
datalad_deprecated/metadata/extractors/tests/test_base.py
datalad_deprecated/metadata/extractors/tests/test_datacite_xml.py
datalad_deprecated/metadata/extractors/tests/test_exif.py
datalad_deprecated/metadata/extractors/tests/test_frictionless_datapackage.py
datalad_deprecated/metadata/extractors/tests/test_image.py
datalad_deprecated/metadata/extractors/tests/test_rfc822.py
datalad_deprecated/metadata/extractors/tests/test_xmp.py
datalad_deprecated/metadata/indexers/__init__.py
datalad_deprecated/metadata/indexers/base.py
datalad_deprecated-0.3.0.dist-info/COPYING
datalad_deprecated-0.3.0.dist-info/LICENSE
datalad_deprecated-0.3.0.dist-info/METADATA
datalad_deprecated-0.3.0.dist-info/WHEEL
datalad_deprecated-0.3.0.dist-info/entry_points.txt
datalad_deprecated-0.3.0.dist-info/top_level.txt
datalad_deprecated-0.3.0.dist-info/RECORD
