Metadata-Version: 2.1
Name: datalad-deprecated
Version: 0.3.0
Summary: DataLad extension package for deprecated functionality that was phased out in the core package
Home-page: https://github.com/datalad/datalad-deprecated
Author: The DataLad Team and Contributors
Author-email: team@datalad.org
License: MIT
Classifier: Programming Language :: Python
Classifier: License :: OSI Approved :: BSD License
Classifier: Programming Language :: Python :: 3
Requires-Python: >=3.7
License-File: LICENSE
License-File: COPYING
Requires-Dist: datalad (>=0.18.0)
Requires-Dist: jsmin
Requires-Dist: whoosh
Requires-Dist: PyYAML
Requires-Dist: mutagen (>=1.36)
Requires-Dist: exifread
Requires-Dist: python-xmp-toolkit
Requires-Dist: Pillow
Provides-Extra: devel
Requires-Dist: pytest ; extra == 'devel'
Requires-Dist: pytest-cov ; extra == 'devel'
Requires-Dist: coverage ; extra == 'devel'
